netframe.py
interface/__init__.py
netframe-0.0.1.dist-info/LICENSE
netframe-0.0.1.dist-info/METADATA
netframe-0.0.1.dist-info/WHEEL
netframe-0.0.1.dist-info/top_level.txt
netframe-0.0.1.dist-info/RECORD
