Metadata-Version: 2.1
Name: netframe
Version: 0.0.1
Summary: NetFrame is a Python framework designed to simplify network configuration
Home-page: https://www.github.com/xeronick/netframe
Author: Xeronick
Author-email: xeronick@outlook.com
License: MIT
Platform: UNKNOWN
Classifier: Programming Language :: Python :: 3
Classifier: License :: OSI Approved :: MIT License
Classifier: Operating System :: OS Independent
Requires-Python: >=3.7
Requires-Dist: Jinja2 (>=3.0.0)
Requires-Dist: netmiko (>=3.4.0)
Requires-Dist: setuptools (>=38.4.0)
